Metadata-Version: 2.1
Name: mathcool
Version: 0.1.1
Summary: This repertory includes the math tool of factorial and Double factorial.It also be used for plotting the density picture of Gauss type function.It also include Hermite and Laguerre polynomial
Home-page: https://github.com/SHUAI1317464601/mathcool.git
Author: Shuai Gao
Author-email: 51180920008@stu.ecnu.edu.cn
License: MIT
Platform: UNKNOWN
Classifier: License :: OSI Approved :: MIT License
Classifier: Programming Language :: Python
Classifier: Programming Language :: Python :: 3
Classifier: Programming Language :: Python :: 3.6
Classifier: Programming Language :: Python :: Implementation :: CPython
Classifier: Programming Language :: Python :: Implementation :: PyPy
Requires-Python: >=3.6.0
